{"artboards":[{"name":"グループ 69","type":"group","bounds":{"width":140.25778198242188,"height":194.13092041015625,"x":25.880340576171875,"y":128.278076171875},"style":{},"id":"e2da3fa2-0d88-4718-8c86-cce141047117","transform":{"a":1,"b":0,"c":0,"d":1,"e":0,"f":0},"children":[{"name":"長方形 15","type":"rectangle","bounds":{"width":29.00299835205078,"height":7.000732421875,"x":26.882732391357422,"y":314.7889709472656},"style":{"fill":{"type":"color","rgba":"rgba(255, 255, 255, 255)","hex":"#FFFFFF"},"stroke":{"color":{"type":"color","rgba":"rgba(35, 24, 21, 255)","hex":"#231815"},"width":0.20000000298023224}},"id":"54832256-2843-4074-8b9d-b8a9f9ce172b","transform":{"a":1,"b":0,"c":0,"d":1,"e":26.882732391357422,"f":314.7889709472656},"children":[]},{"name":"グループ 68","type":"group","bounds":{"width":140.25778198242188,"height":194.13092041015625,"x":25.880340576171875,"y":128.278076171875},"style":{},"id":"10ad3dcd-bd3c-417a-9336-0261b42ef6df","transform":{"a":1,"b":0,"c":0,"d":1,"e":0,"f":0},"children":[{"name":"好きも、暮らしも、全部こだわる。","type":"text","bounds":{"width":76,"height":7,"x":26.558624267578125,"y":175.0374755859375},"style":{"fontFamily":"NotoSansJP-Bold","fontSize":4.800000190734863,"textAlign":"left","lineHeight":6,"letterSpacing":-10,"fill":{"type":"color","rgba":"rgba(35, 24, 21, 255)","hex":"#231815"}},"id":"0444cef0-7379-4d5d-98a5-21f4762ba6d2","transform":{"a":1,"b":0,"c":0,"d":1,"e":26.558624267578125,"f":181.0374755859375},"text":"好きも、暮らしも、全部こだわる。","children":[]},{"name":"大事にしているのはどう売るかより\n「どう暮らしたいか」。妥協しない。\nちゃんと、自分たちの家をつくる。","type":"text","bounds":{"width":33,"height":13,"x":75.96292114257812,"y":237.0203857421875},"style":{"fontFamily":"NotoSansJP-Bold","fontSize":1.7999999523162842,"textAlign":"left","lineHeight":5,"letterSpacing":100,"fill":{"type":"color","rgba":"rgba(0, 0, 0, 255)","hex":"#000000"}},"id":"6f3e5dbe-4a10-42cf-91cf-5d46d57d889a","transform":{"a":1,"b":0,"c":0,"d":1,"e":75.96292114257812,"f":239.0203857421875},"text":"大事にしているのはどう売るかより\n「どう暮らしたいか」。妥協しない。\nちゃんと、自分たちの家をつくる。","children":[]},{"name":"グループ 8","type":"group","bounds":{"width":103.5,"height":42,"x":62.5,"y":280.40899658203125},"style":{},"id":"9f6fbfbf-84a8-4ef1-8a96-5687c655e2f6","transform":{"a":1,"b":0,"c":0,"d":1,"e":0,"f":0},"children":[{"name":"グループ 7","type":"group","bounds":{"width":103.5,"height":42,"x":62.5,"y":280.40899658203125},"style":{},"id":"2127a3e9-d41d-409a-a498-c7b094ac9676","transform":{"a":1,"b":0,"c":0,"d":1,"e":0,"f":0},"children":[{"name":"長方形 12","type":"rectangle","bounds":{"width":109.50010681152344,"height":73.00006103515625,"x":58.6541748046875,"y":267.25408935546875},"style":{"fill":{"type":"image"}},"id":"fc0152c8-9ded-48ee-83e8-c1ca41cca4c0","transform":{"a":1,"b":0,"c":0,"d":1,"e":58.6541748046875,"f":267.25408935546875},"children":[]},{"name":"長方形 13","type":"rectangle","bounds":{"width":103.5,"height":42,"x":62.5,"y":280.40899658203125},"style":{},"id":"d724c320-2c4e-4b11-9738-e59b49f14496","transform":{"a":1,"b":0,"c":0,"d":1,"e":62.5,"f":280.40899658203125},"children":[]}]}]},{"name":"No Fun No Life","type":"text","bounds":{"width":139,"height":19,"x":25.880340576171875,"y":128.278076171875},"style":{"fontFamily":"Helvetica-Bold","fontSize":19.5,"textAlign":"right","lineHeight":34.125,"fill":{"type":"color","rgba":"rgba(0, 0, 0, 255)","hex":"#000000"}},"id":"31f3db20-b08d-4a62-b96f-1edfe3ba7577","transform":{"a":1,"b":0,"c":0,"d":1,"e":164.88034057617188,"f":143.278076171875},"text":"No Fun No Life","children":[]},{"name":"CONCEPT","type":"text","bounds":{"width":30.009599685668945,"height":6.0479736328125,"x":26.287580490112305,"y":305.6714782714844},"style":{"fontFamily":"Helvetica-Bold","fontSize":6,"textAlign":"center","lineHeight":10.5,"fill":{"type":"color","rgba":"rgba(35, 24, 21, 255)","hex":"#231815"}},"id":"e70d017d-eff6-4b61-b4e6-fb147b0f1b99","transform":{"a":1,"b":0.001600000075995922,"c":-0.001600000075995922,"d":1,"e":41.289180755615234,"f":310.6954650878906},"text":"CONCEPT","children":[]},{"name":"View More","type":"text","bounds":{"width":12,"height":3,"x":35.391632080078125,"y":317.3255615234375},"style":{"fontFamily":"Helvetica-Bold","fontSize":2.63316011428833,"textAlign":"center","lineHeight":4.608030319213867,"fill":{"type":"color","rgba":"rgba(35, 24, 21, 255)","hex":"#231815"}},"id":"1637d94c-6040-4c00-98dc-c527c3a240f8","transform":{"a":1,"b":0,"c":0,"d":1,"e":41.391632080078125,"f":319.3255615234375},"text":"View More","children":[]},{"name":"グループ 13","type":"group","bounds":{"width":35,"height":27,"x":26,"y":229.6204833984375},"style":{},"id":"b557c009-2609-418e-a5a2-91211c429dd1","transform":{"a":1,"b":0,"c":0,"d":1,"e":0,"f":0},"children":[{"name":"グループ 12","type":"group","bounds":{"width":35,"height":27,"x":26,"y":229.6204833984375},"style":{},"id":"8872b79c-fdfc-4b47-94a4-06df520c0939","transform":{"a":1,"b":0,"c":0,"d":1,"e":0,"f":0},"children":[{"name":"グループ 11","type":"group","bounds":{"width":35,"height":27,"x":26,"y":229.6204833984375},"style":{},"id":"0f1d629b-4dba-419c-a3a3-16fd07800836","transform":{"a":1,"b":0,"c":0,"d":1,"e":0,"f":0},"children":[{"name":"長方形 18","type":"rectangle","bounds":{"width":52.30152130126953,"height":29.653884887695312,"x":17.211584091186523,"y":227.2722625732422},"style":{"fill":{"type":"image"}},"id":"d52b8f4b-1ff0-47fd-9f1e-90fe9ac2b12f","transform":{"a":1,"b":0,"c":0,"d":1,"e":17.211584091186523,"f":227.2722625732422},"children":[]},{"name":"長方形 19","type":"rectangle","bounds":{"width":35,"height":27,"x":26,"y":229.6204833984375},"style":{},"id":"d0a03626-c409-479f-a413-0858499fe204","transform":{"a":1,"b":0,"c":0,"d":1,"e":26,"f":229.6204833984375},"children":[]}]}]}]},{"name":"家って、ただ住む箱じゃない。毎日帰って、笑って、落ち着いて、人生のほとんどを過ご\nす場所。だからファンライフは、むやみに棟数を増やさない。性能は、本当にいいと思え\nるものを。でも、間取りもデザイン性能も、「こうじゃないとダメ」とは言いません。","type":"text","bounds":{"width":79,"height":13,"x":26.776397705078125,"y":185.6112060546875},"style":{"fontFamily":"NotoSansJP-Bold","fontSize":1.7999999523162842,"textAlign":"left","lineHeight":5,"letterSpacing":100,"fill":{"type":"color","rgba":"rgba(0, 0, 0, 255)","hex":"#000000"}},"id":"9a37b53e-ae31-422d-a0ce-b15880d149b1","transform":{"a":1,"b":0,"c":0,"d":1,"e":26.776397705078125,"f":187.6112060546875},"text":"家って、ただ住む箱じゃない。毎日帰って、笑って、落ち着いて、人生のほとんどを過ご\nす場所。だからファンライフは、むやみに棟数を増やさない。性能は、本当にいいと思え\nるものを。でも、間取りもデザイン性能も、「こうじゃないとダメ」とは言いません。","children":[]},{"name":"グループ 43","type":"group","bounds":{"width":50.00000762939453,"height":50,"x":116.13811492919922,"y":176.7666015625},"style":{},"id":"dbade251-33c0-4b83-9fbb-2cea10433f19","transform":{"a":1,"b":0,"c":0,"d":1,"e":0,"f":0},"children":[{"name":"グループ 42","type":"group","bounds":{"width":50.00000762939453,"height":50,"x":116.13811492919922,"y":176.7666015625},"style":{},"id":"ee41d31a-7578-4072-9210-0d1c2da7e878","transform":{"a":1,"b":0,"c":0,"d":1,"e":0,"f":0},"children":[{"name":"長方形 44","type":"rectangle","bounds":{"width":182.89300537109375,"height":121.92868041992188,"x":52.06229782104492,"y":143.85140991210938},"style":{"fill":{"type":"image"}},"id":"09c8f85b-f96e-4157-b037-aa464882b654","transform":{"a":1,"b":0,"c":0,"d":1,"e":52.06229782104492,"f":143.85140991210938},"children":[]},{"name":"長方形 45","type":"rectangle","bounds":{"width":50.00000762939453,"height":50,"x":116.13811492919922,"y":176.7666015625},"style":{},"id":"83e69f32-6a62-45bf-b14d-3421397f516f","transform":{"a":1,"b":0,"c":0,"d":1,"e":116.13811492919922,"f":176.7666015625},"children":[]}]}]}]}]}]}